nerva/__init__.py
nerva/__main__.py
nerva/daemon.py
nerva/utils.py
nerva/wallet.py
nerva_py-1.1.0.dist-info/METADATA
nerva_py-1.1.0.dist-info/WHEEL
nerva_py-1.1.0.dist-info/licenses/LICENSE
nerva_py-1.1.0.dist-info/RECORD
