Metadata-Version: 2.3
Name: nerva-py
Version: 1.1.0
Summary: Python bindings for the JSON RPC interface of the Nerva cryptocurrency.
Author-email: Sayan Bhattacharyya <sayan@sn1f3rt.dev>
License: MIT
Keywords: bindings,cryptocurrency,json-rpc,nerva,python
Classifier: Development Status :: 5 - Production/Stable
Classifier: Intended Audience :: Developers
Classifier: License :: OSI Approved :: MIT License
Classifier: Operating System :: OS Independent
Classifier: Programming Language :: Python :: 3
Classifier: Programming Language :: Python :: 3.8
Classifier: Programming Language :: Python :: 3.9
Classifier: Programming Language :: Python :: 3.10
Classifier: Programming Language :: Python :: 3.11
Classifier: Programming Language :: Python :: 3.12
Classifier: Programming Language :: Python :: 3.13
Classifier: Topic :: Software Development :: Libraries :: Python Modules
Requires-Python: >=3.8
Requires-Dist: httpx>=0.27.2
